LICENSE
MANIFEST.in
README
setup.py
django_trawler.egg-info/PKG-INFO
django_trawler.egg-info/SOURCES.txt
django_trawler.egg-info/dependency_links.txt
django_trawler.egg-info/requires.txt
django_trawler.egg-info/top_level.txt
trawler/__init__.py
trawler/admin.py
trawler/models.py
trawler/test_urls.py
trawler/tests.py
trawler/urls.py
trawler/views.py
trawler/templates/404.html
trawler/templates/500.html
trawler/templates/trawler/campaign_detail.html