Metadata-Version: 1.0
Name: django-trawler
Version: 0.1a
Summary: Django App for running phishing campaigns (for staff security awareness training).
Home-page: https://bitbucket.org/onelson/django-trawler
Author: Owen Nelson
Author-email: onelson@gmail.com
License: MIT
Keywords: phishing,security,django
Platform: UNKNOWN
Classifier: Development Status :: 3 - Alpha
Classifier: Environment :: Web Environment
Classifier: Framework :: Django
Classifier: Intended Audience :: Developers
Classifier: License :: OSI Approved :: MIT License
Classifier: Operating System :: OS Independent
Classifier: Programming Language :: Python
Classifier: Topic :: Internet :: WWW/HTTP
Classifier: Topic :: Internet :: WWW/HTTP :: Dynamic Content
Classifier: Topic :: Internet :: WWW/HTTP :: WSGI
Classifier: Topic :: Software Development :: Libraries :: Application Frameworks
Classifier: Topic :: Software Development :: Libraries :: Python Modules
